odpswrap/__init__.py
odpswrap/computing/__init__.py
odpswrap/computing/api.py
odpswrap/computing/client.py
odpswrap/computing/data_types.py
odpswrap-0.0.1.dist-info/LICENSE
odpswrap-0.0.1.dist-info/METADATA
odpswrap-0.0.1.dist-info/WHEEL
odpswrap-0.0.1.dist-info/top_level.txt
odpswrap-0.0.1.dist-info/RECORD
