Metadata-Version: 2.1
Name: odpswrap
Version: 0.0.1
Summary: This library provides convenient access to the Citybrain Platform API
Author-email: citybrain <opensource@citybrain.org>
Project-URL: Homepage, https://github.com/citybrain-platform/python-library
Project-URL: Bug Tracker, https://github.com/citybrain-platform/python-library/issues
Classifier: Programming Language :: Python :: 3
Classifier: License :: OSI Approved :: MIT License
Classifier: Operating System :: OS Independent
Requires-Python: >=3.7
License-File: LICENSE
Requires-Dist: uplink
Requires-Dist: requests
Requires-Dist: dacite
